[
  {
    "Event": "UpdateState",
    "Data": {
      "MatchGuid": "1F7ED23011F1435166EBAB919DB5566D",
      "Players": [
        {
          "Name": "nickm",
          "PrimaryId": "Steam|76561197960409023|0",
          "Shortcut": 1,
          "TeamNum": 0,
          "Score": 0,
          "Goals": 0,
          "Shots": 0,
          "Assists": 0,
          "Saves": 0,
          "Touches": 0,
          "CarTouches": 0,
          "Demos": 0,
          "bOnGround": true,
          "bHasCar": true,
          "Speed": 0.009764032438397408,
          "Boost": 33
        },
        {
          "Name": "Zone Killa",
          "PrimaryId": "Epic|9dfa38bf97f9442997b464ea869eb96a|0",
          "Shortcut": 5,
          "TeamNum": 1,
          "Score": 324,
          "Goals": 1,
          "Shots": 1,
          "Assists": 0,
          "Saves": 0,
          "Touches": 264,
          "CarTouches": 0,
          "Demos": 0
        }
      ],
      "Game": {
        "Teams": [
          {
            "Name": "Blue",
            "TeamNum": 0,
            "Score": 0,
            "ColorPrimary": "1873FF",
            "ColorSecondary": "E5E5E5"
          },
          {
            "Name": "Orange",
            "TeamNum": 1,
            "Score": 1,
            "ColorPrimary": "C26418",
            "ColorSecondary": "E5E5E5"
          }
        ],
        "TimeSeconds": 81,
        "bOvertime": false,
        "Ball": {
          "Speed": 50.02859115600586,
          "TeamNum": 1
        },
        "bReplay": false,
        "bHasWinner": false,
        "Winner": "",
        "Arena": "cs_p",
        "bHasTarget": true,
        "Target": {
          "Name": "nickm",
          "Shortcut": 1,
          "TeamNum": 0
        }
      }
    }
  },
  {
    "Event": "UpdateState",
    "Data": {
      "MatchGuid": "1F7ED23011F1435166EBAB919DB5566D",
      "Players": [
        {
          "Name": "nickm",
          "PrimaryId": "Steam|76561197960409023|0",
          "Shortcut": 1,
          "TeamNum": 0,
          "Score": 0,
          "Goals": 0,
          "Shots": 0,
          "Assists": 0,
          "Saves": 0,
          "Touches": 0,
          "CarTouches": 0,
          "Demos": 0,
          "bOnGround": true,
          "bHasCar": true,
          "Speed": 0.009764032438397408,
          "Boost": 33
        },
        {
          "Name": "Zone Killa",
          "PrimaryId": "Epic|9dfa38bf97f9442997b464ea869eb96a|0",
          "Shortcut": 5,
          "TeamNum": 1,
          "Score": 324,
          "Goals": 1,
          "Shots": 1,
          "Assists": 0,
          "Saves": 0,
          "Touches": 264,
          "CarTouches": 0,
          "Demos": 0
        }
      ],
      "Game": {
        "Teams": [
          {
            "Name": "Blue",
            "TeamNum": 0,
            "Score": 0,
            "ColorPrimary": "1873FF",
            "ColorSecondary": "E5E5E5"
          },
          {
            "Name": "Orange",
            "TeamNum": 1,
            "Score": 1,
            "ColorPrimary": "C26418",
            "ColorSecondary": "E5E5E5"
          }
        ],
        "TimeSeconds": 81,
        "bOvertime": false,
        "Ball": {
          "Speed": 50.097808837890625,
          "TeamNum": 1
        },
        "bReplay": false,
        "bHasWinner": false,
        "Winner": "",
        "Arena": "cs_p",
        "bHasTarget": true,
        "Target": {
          "Name": "nickm",
          "Shortcut": 1,
          "TeamNum": 0
        }
      }
    }
  },
  {
    "Event": "UpdateState",
    "Data": {
      "MatchGuid": "1F7ED23011F1435166EBAB919DB5566D",
      "Players": [
        {
          "Name": "nickm",
          "PrimaryId": "Steam|76561197960409023|0",
          "Shortcut": 1,
          "TeamNum": 0,
          "Score": 0,
          "Goals": 0,
          "Shots": 0,
          "Assists": 0,
          "Saves": 0,
          "Touches": 0,
          "CarTouches": 0,
          "Demos": 0,
          "bOnGround": true,
          "bHasCar": true,
          "Speed": 0.009764032438397408,
          "Boost": 33
        },
        {
          "Name": "Zone Killa",
          "PrimaryId": "Epic|9dfa38bf97f9442997b464ea869eb96a|0",
          "Shortcut": 5,
          "TeamNum": 1,
          "Score": 324,
          "Goals": 1,
          "Shots": 1,
          "Assists": 0,
          "Saves": 0,
          "Touches": 264,
          "CarTouches": 0,
          "Demos": 0
        }
      ],
      "Game": {
        "Teams": [
          {
            "Name": "Blue",
            "TeamNum": 0,
            "Score": 0,
            "ColorPrimary": "1873FF",
            "ColorSecondary": "E5E5E5"
          },
          {
            "Name": "Orange",
            "TeamNum": 1,
            "Score": 1,
            "ColorPrimary": "C26418",
            "ColorSecondary": "E5E5E5"
          }
        ],
        "TimeSeconds": 81,
        "bOvertime": false,
        "Ball": {
          "Speed": 50.23811340332031,
          "TeamNum": 1
        },
        "bReplay": false,
        "bHasWinner": false,
        "Winner": "",
        "Arena": "cs_p",
        "bHasTarget": true,
        "Target": {
          "Name": "nickm",
          "Shortcut": 1,
          "TeamNum": 0
        }
      }
    }
  },
  {
    "Event": "UpdateState",
    "Data": {
      "MatchGuid": "1F7ED23011F1435166EBAB919DB5566D",
      "Players": [
        {
          "Name": "nickm",
          "PrimaryId": "Steam|76561197960409023|0",
          "Shortcut": 1,
          "TeamNum": 0,
          "Score": 0,
          "Goals": 0,
          "Shots": 0,
          "Assists": 0,
          "Saves": 0,
          "Touches": 0,
          "CarTouches": 0,
          "Demos": 0,
          "bOnGround": true,
          "bHasCar": true,
          "Speed": 0.009764032438397408,
          "Boost": 33
        },
        {
          "Name": "Zone Killa",
          "PrimaryId": "Epic|9dfa38bf97f9442997b464ea869eb96a|0",
          "Shortcut": 5,
          "TeamNum": 1,
          "Score": 324,
          "Goals": 1,
          "Shots": 1,
          "Assists": 0,
          "Saves": 0,
          "Touches": 264,
          "CarTouches": 0,
          "Demos": 0
        }
      ],
      "Game": {
        "Teams": [
          {
            "Name": "Blue",
            "TeamNum": 0,
            "Score": 0,
            "ColorPrimary": "1873FF",
            "ColorSecondary": "E5E5E5"
          },
          {
            "Name": "Orange",
            "TeamNum": 1,
            "Score": 1,
            "ColorPrimary": "C26418",
            "ColorSecondary": "E5E5E5"
          }
        ],
        "TimeSeconds": 81,
        "bOvertime": false,
        "Ball": {
          "Speed": 50.45318603515625,
          "TeamNum": 1
        },
        "bReplay": false,
        "bHasWinner": false,
        "Winner": "",
        "Arena": "cs_p",
        "bHasTarget": true,
        "Target": {
          "Name": "nickm",
          "Shortcut": 1,
          "TeamNum": 0
        }
      }
    }
  },
  {
    "Event": "UpdateState",
    "Data": {
      "MatchGuid": "1F7ED23011F1435166EBAB919DB5566D",
      "Players": [
        {
          "Name": "nickm",
          "PrimaryId": "Steam|76561197960409023|0",
          "Shortcut": 1,
          "TeamNum": 0,
          "Score": 0,
          "Goals": 0,
          "Shots": 0,
          "Assists": 0,
          "Saves": 0,
          "Touches": 0,
          "CarTouches": 0,
          "Demos": 0,
          "bOnGround": true,
          "bHasCar": true,
          "Speed": 0.009764032438397408,
          "Boost": 33
        },
        {
          "Name": "Zone Killa",
          "PrimaryId": "Epic|9dfa38bf97f9442997b464ea869eb96a|0",
          "Shortcut": 5,
          "TeamNum": 1,
          "Score": 324,
          "Goals": 1,
          "Shots": 1,
          "Assists": 0,
          "Saves": 0,
          "Touches": 264,
          "CarTouches": 0,
          "Demos": 0
        }
      ],
      "Game": {
        "Teams": [
          {
            "Name": "Blue",
            "TeamNum": 0,
            "Score": 0,
            "ColorPrimary": "1873FF",
            "ColorSecondary": "E5E5E5"
          },
          {
            "Name": "Orange",
            "TeamNum": 1,
            "Score": 1,
            "ColorPrimary": "C26418",
            "ColorSecondary": "E5E5E5"
          }
        ],
        "TimeSeconds": 81,
        "bOvertime": false,
        "Ball": {
          "Speed": 50.59946060180664,
          "TeamNum": 1
        },
        "bReplay": false,
        "bHasWinner": false,
        "Winner": "",
        "Arena": "cs_p",
        "bHasTarget": true,
        "Target": {
          "Name": "nickm",
          "Shortcut": 1,
          "TeamNum": 0
        }
      }
    }
  }
]
